kami/Kami.py
kami/__init__.py
kami/kamutils/__init__.py
kami/kamutils/_utils.py
kami/metrics/__init__.py
kami/metrics/_base_metrics.py
kami/metrics/evaluation.py
kami/parser/__init__.py
kami/parser/parser_text.py
kami/parser/parser_xml.py
kami/preprocessing/__init__.py
kami/preprocessing/transformation.py
kami/transcription/__init__.py
kami/transcription/prediction.py
kamilib-0.1.13.dist-info/LICENSE
kamilib-0.1.13.dist-info/METADATA
kamilib-0.1.13.dist-info/WHEEL
kamilib-0.1.13.dist-info/top_level.txt
kamilib-0.1.13.dist-info/RECORD
