Metadata-Version: 2.1
Name: kamilib
Version: 0.1.13
Summary: HTR / OCR models evaluation agnostic Python package, originally based on the Kraken transcription system.
Home-page: https://github.com/KaMI-tools-project/KaMi-lib
Author: Lucas Terriel, Alix Chagué
Author-email: lucas.terriel@chartes.psl.eu, alix.chague@inria.fr
License: MIT
Keywords: HTR,OCR,Evaluation framework,metrics,handwritten text recognition,optical character recognition
Classifier: Programming Language :: Python
Classifier: License :: OSI Approved :: MIT License
Classifier: Intended Audience :: Developers
Classifier: Intended Audience :: Education
Classifier: Intended Audience :: Science/Research
Classifier: Operating System :: OS Independent
Classifier: Topic :: Software Development :: Libraries
Classifier: Topic :: Software Development :: Libraries :: Python Modules
Requires-Python: >=3.8
License-File: LICENSE
Requires-Dist: termcolor (==1.1.0)
Requires-Dist: kraken (==4.3.5)
Requires-Dist: unidecode (==1.3.4)
Requires-Dist: levenshtein (==0.20.9)
